{
  "es": [
    {
      "id": 7,
      "img": "https://static.wixstatic.com/media/5dd8a0_67020ed5ab7c46e4be8085fb20563eb7~mv2.webp",
      "name": "Promoción Level 80",
      "description": "¡Salta directamente al nivel 80 y prepárate para la acción! Olvídate de las misiones repetitivas y entra al contenido épico ahora mismo..",
      "btn_txt": "¡Salta Ahora!",
      "send_item": false,
      "items": [],
      "server_id": 1,
      "min_lvl": 1,
      "max_lvl": 10,
      "type": "LEVEL",
      "amount": 0
    },
    {
      "id": 8,
      "img": "https://encrypted-tbn0.gstatic.com/images?q=tbn:ANd9GcSvKlw1918kd4HhWR7PtOA5ffUPeFNB8kVVLw&s",
      "name": "Beneficio de levelear - Arcos/Ballestas/Arma arrojadiza/Astas",
      "description": "¡Por levelear y disfrutar el contenido y estas en el rango  level 70 y 79 puedes reclamar este beneficio",
      "btn_txt": "¡Obtener Beneficio!",
      "send_item": true,
      "items": [
        {
          "code": "51395",
          "quantity": 1
        },
        {
          "code": "51395",
          "quantity": 1
        },
        {
          "code": "51535",
          "quantity": 1
        },
        {
          "code": "51411",
          "quantity": 1
        },
        {
          "code": "51412",
          "quantity": 1
        },
        {
          "code": "51481",
          "quantity": 1
        },
        {
          "code": "51480",
          "quantity": 1
        }
      ],
      "server_id": 1,
      "min_lvl": 60,
      "max_lvl": 79,
      "type": "ITEM",
      "amount": 0
    },
    {
      "id": 9,
      "img": "https://encrypted-tbn0.gstatic.com/images?q=tbn:ANd9GcQQGlJVf0YynsG8lBX2sTbNYXhhkLtJq57iVdjUDuERv0XJu0UhP11JLHGUXpaDS_jYet4&usqp=CAU",
      "name": "Beneficio de levelear - Bastones/Arma de fuego",
      "description": "¡Por levelear y disfrutar el contenido y estas en el rango  level 70 y 79 puedes reclamar este beneficio",
      "btn_txt": "¡Obtener Beneficio!",
      "send_item": true,
      "items": [
        {
          "code": "51432",
          "quantity": 1
        },
        {
          "code": "51404",
          "quantity": 1
        },
        {
          "code": "51402",
          "quantity": 1
        },
        {
          "code": "51431",
          "quantity": 1
        },
        {
          "code": "51456",
          "quantity": 1
        },
        {
          "code": "51400",
          "quantity": 1
        },
        {
          "code": "51401",
          "quantity": 1
        },
        {
          "code": "51405",
          "quantity": 1
        },
        {
          "code": "51403",
          "quantity": 1
        },
        {
          "code": "51457",
          "quantity": 1
        },
        {
          "code": "51450",
          "quantity": 1
        },
        {
          "code": "51449",
          "quantity": 1
        }
      ],
      "server_id": 1,
      "min_lvl": 15,
      "max_lvl": 79,
      "type": "ITEM",
      "amount": 0
    },
    {
      "id": 10,
      "img": "https://es.gizmodo.com/app/uploads/2019/05/kgc6dnrc1tuz5xdlxjaq.jpg",
      "name": "Beneficio de levelear - Hachas/Espada Dos manos",
      "description": "¡Por levelear y disfrutar el contenido y estas en el rango  level 70 y 79 puedes reclamar este beneficio",
      "btn_txt": "¡Obtener Beneficio!",
      "send_item": true,
      "items": [
        {
          "code": "51389",
          "quantity": 1
        },
        {
          "code": "51388",
          "quantity": 1
        },
        {
          "code": "51439",
          "quantity": 1
        },
        {
          "code": "51526",
          "quantity": 1
        },
        {
          "code": "51440",
          "quantity": 1
        },
        {
          "code": "51515",
          "quantity": 1
        },
        {
          "code": "51392",
          "quantity": 1
        },
        {
          "code": "51393",
          "quantity": 1
        },
        {
          "code": "51516",
          "quantity": 1
        },
        {
          "code": "51448",
          "quantity": 1
        },
        {
          "code": "51522",
          "quantity": 1
        }
      ],
      "server_id": 1,
      "min_lvl": 15,
      "max_lvl": 79,
      "type": "ITEM",
      "amount": 0
    },
    {
      "id": 11,
      "img": "https://encrypted-tbn0.gstatic.com/images?q=tbn:ANd9GcRy5rp2ozxs5YbQmibKBN4YiVpZLzi_fRKOgZWyTXKApwUwHpojioaX7w8gWSW_S8MKnik&usqp=CAU",
      "name": "Beneficio de levelear - Dagas - Maza",
      "description": "¡Por levelear y disfrutar el contenido y estas en el rango  level 70 y 79 puedes reclamar este beneficio",
      "btn_txt": "¡Obtener Beneficio!",
      "send_item": true,
      "items": [
        {
          "code": "51518",
          "quantity": 1
        },
        {
          "code": "51528",
          "quantity": 1
        },
        {
          "code": "51398",
          "quantity": 1
        },
        {
          "code": "51442",
          "quantity": 1
        },
        {
          "code": "51399",
          "quantity": 1
        },
        {
          "code": "51529",
          "quantity": 1
        },
        {
          "code": "51524",
          "quantity": 1
        },
        {
          "code": "51444",
          "quantity": 1
        },
        {
          "code": "51390",
          "quantity": 1
        },
        {
          "code": "51520",
          "quantity": 1
        },
        {
          "code": "51446",
          "quantity": 1
        },
        {
          "code": "51454",
          "quantity": 1
        }
      ],
      "server_id": 1,
      "min_lvl": 15,
      "max_lvl": 79,
      "type": "ITEM",
      "amount": 0
    },
    {
      "id": 12,
      "img": "https://encrypted-tbn0.gstatic.com/images?q=tbn:ANd9GcSyUYhMzg5L5b-YvW47jWahUTyGHRGqhUbXt_Qo6LwpeAqr2UcS_tgx4iPUqRHDS9gob9Y&usqp=CAU",
      "name": "Beneficio de levelear - Varitas",
      "description": "¡Por levelear y disfrutar el contenido y estas en el rango  level 70 y 79 puedes reclamar este beneficio",
      "btn_txt": "¡Obtener Beneficio!",
      "send_item": true,
      "items": [
        {
          "code": "51454",
          "quantity": 1
        },
        {
          "code": "51451",
          "quantity": 1
        },
        {
          "code": "51531",
          "quantity": 1
        },
        {
          "code": "51410",
          "quantity": 1
        }
      ],
      "server_id": 1,
      "min_lvl": 15,
      "max_lvl": 79,
      "type": "ITEM",
      "amount": 0
    },
    {
      "id": 1,
      "img": "https://encrypted-tbn0.gstatic.com/images?q=tbn:ANd9GcTbw94DnB4ZP0L2Q-Is5D0zhT-iMikJ1y5V-g&s",
      "name": "Promoción de Leveo - Armas",
      "description": "¡Haz tu progreso más fácil con esta increíble promoción! Consigue armas reliquia y lleva tu nivel al siguiente nivel de forma más sencilla.",
      "btn_txt": "Obtener",
      "send_item": true,
      "items": [
        {
          "code": "42944",
          "quantity": 1
        },
        {
          "code": "42946",
          "quantity": 1
        },
        {
          "code": "42948",
          "quantity": 1
        },
        {
          "code": "42943",
          "quantity": 1
        },
        {
          "code": "42945",
          "quantity": 1
        },
        {
          "code": "48716",
          "quantity": 1
        },
        {
          "code": "48718",
          "quantity": 1
        }
      ],
      "server_id": 1,
      "min_lvl": 1,
      "max_lvl": 80,
      "type": "ITEM",
      "amount": 0
    },
    {
      "id": 2,
      "img": "https://chaosboost.com/wp-content/uploads/2024/05/wowclassic-power-leveling.jpg",
      "name": "¡Reclama 800 Emblemas de Escarcha Ahora!",
      "description": "¡No dejes pasar esta oferta única! Consigue 800 emblemas de escarcha para potenciar tu set PvE. Promoción exclusiva para una cuenta, ¡aprovecha antes de que se acabe!",
      "btn_txt": "Obtener",
      "send_item": true,
      "items": [
        {
          "code": "49426",
          "quantity": 800
        },
        {
          "code": "47241",
          "quantity": 300
        }
      ],
      "server_id": 1,
      "min_lvl": 1,
      "max_lvl": 80,
      "type": "ITEM",
      "amount": 0
    },
    {
      "id": 3,
      "img": "https://wow.zamimg.com/uploads/screenshots/normal/102318-gran-oso-de-blizzard.jpg",
      "name": "¡Montura Exclusiva por Cuenta!",
      "description": "¡No dejes pasar esta oportunidad! Obtén una montura gratis como parte de esta promoción especial.",
      "btn_txt": "Obtener",
      "send_item": true,
      "items": [
        {
          "code": "43599",
          "quantity": 1
        },
        {
          "code": "44168",
          "quantity": 1
        }
      ],
      "server_id": 1,
      "min_lvl": 1,
      "max_lvl": 80,
      "type": "ITEM",
      "amount": 0
    },
    {
      "id": 4,
      "img": "https://www.wowchakra.com/wp-content/uploads/2020/04/WowChakraNovelaIlustrada.jpg",
      "name": "Promoción de Leveo - Equipo",
      "description": "¡Descubre la experiencia Leveo! Nuestra promoción está diseñada para brindarte el equipo ideal y ayudarte a alcanzar tus metas de manera eficiente y profesional.",
      "btn_txt": "Obtener",
      "send_item": true,
      "items": [
        {
          "code": "42949",
          "quantity": 1
        },
        {
          "code": "42951",
          "quantity": 1
        },
        {
          "code": "42952",
          "quantity": 1
        },
        {
          "code": "42984",
          "quantity": 1
        },
        {
          "code": "42985",
          "quantity": 1
        },
        {
          "code": "48677",
          "quantity": 1
        },
        {
          "code": "48683",
          "quantity": 1
        },
        {
          "code": "48685",
          "quantity": 1
        },
        {
          "code": "48687",
          "quantity": 1
        },
        {
          "code": "48689",
          "quantity": 1
        },
        {
          "code": "48691",
          "quantity": 1
        },
        {
          "code": "50255",
          "quantity": 1
        }
      ],
      "server_id": 1,
      "min_lvl": 1,
      "max_lvl": 80,
      "type": "ITEM",
      "amount": 0
    },
    {
      "id": 5,
      "img": "https://blz-contentstack-images.akamaized.net/v3/assets/bltf408a0557f4e4998/blt44b9b4635a152dfc/63c71f0ca1a308140627270d/world-of-warcraft-service-character-transfer-section1-feature3.jpg?imwidth=1920&imdensity=2.625",
      "name": "Promoción de Leveo - Abalorios y Otros",
      "description": "¡Explora nuestra oferta especial! Encuentra los mejores abalorios y accesorios para potenciar tu experiencia y marcar la diferencia en cada detalle.",
      "btn_txt": "Obtener",
      "send_item": true,
      "items": [
        {
          "code": "42985",
          "quantity": 1
        },
        {
          "code": "50255",
          "quantity": 1
        },
        {
          "code": "42991",
          "quantity": 1
        },
        {
          "code": "42992",
          "quantity": 1
        },
        {
          "code": "42947",
          "quantity": 1
        }
      ],
      "server_id": 1,
      "min_lvl": 1,
      "max_lvl": 80,
      "type": "ITEM",
      "amount": 0
    },
    {
      "id": 6,
      "img": "https://cdn.altertime.es/e4f080d2-94e8-4fd0-aa16-a489d183d4bf.png",
      "name": "Promoción Especial de Bolsas",
      "description": "¡No pierdas la oportunidad de obtener estas bolsas exclusivas y mejora tu inventario!",
      "btn_txt": "Conseguir ahora",
      "send_item": true,
      "items": [
        {
          "code": "41600",
          "quantity": 4
        }
      ],
      "server_id": 1,
      "min_lvl": 1,
      "max_lvl": 80,
      "type": "ITEM",
      "amount": 0
    }
  ],
  "en": [
    {
      "id": 7,
      "img": "https://static.wixstatic.com/media/5dd8a0_67020ed5ab7c46e4be8085fb20563eb7~mv2.webp",
      "name": "Level 80 Boost",
      "description": "Jump straight to level 80 and dive into the action! Skip the grind and get ready for epic content now.",
      "btn_txt": "Boost Now!",
      "send_item": false,
      "items": [],
      "server_id": 1,
      "min_lvl": 1,
      "max_lvl": 10,
      "type": "LEVEL",
      "amount": 0
    },
    {
      "id": 8,
      "img": "https://encrypted-tbn0.gstatic.com/images?q=tbn:ANd9GcSvKlw1918kd4HhWR7PtOA5ffUPeFNB8kVVLw&s",
      "name": "Leveling Reward - Bows/Crossbows/Thrown Weapons/Polearms",
      "description": "By leveling up and enjoying the content, if you're in the level range 70 to 79, you can claim this reward.",
      "btn_txt": "Claim Reward!",
      "send_item": true,
      "items": [
        {
          "code": "51395",
          "quantity": 1
        },
        {
          "code": "51395",
          "quantity": 1
        },
        {
          "code": "51535",
          "quantity": 1
        },
        {
          "code": "51411",
          "quantity": 1
        },
        {
          "code": "51412",
          "quantity": 1
        },
        {
          "code": "51481",
          "quantity": 1
        },
        {
          "code": "51480",
          "quantity": 1
        }
      ],
      "server_id": 1,
      "min_lvl": 15,
      "max_lvl": 79,
      "type": "ITEM",
      "amount": 0
    },
    {
      "id": 9,
      "img": "https://encrypted-tbn0.gstatic.com/images?q=tbn:ANd9GcQQGlJVf0YynsG8lBX2sTbNYXhhkLtJq57iVdjUDuERv0XJu0UhP11JLHGUXpaDS_jYet4&usqp=CAU",
      "name": "Leveling Reward - Staves/Guns",
      "description": "By leveling up and enjoying the content, if you're in the level range 70 to 79, you can claim this reward.",
      "btn_txt": "Claim Reward!",
      "send_item": true,
      "items": [
        {
          "code": "51432",
          "quantity": 1
        },
        {
          "code": "51404",
          "quantity": 1
        },
        {
          "code": "51402",
          "quantity": 1
        },
        {
          "code": "51431",
          "quantity": 1
        },
        {
          "code": "51456",
          "quantity": 1
        },
        {
          "code": "51400",
          "quantity": 1
        },
        {
          "code": "51401",
          "quantity": 1
        },
        {
          "code": "51405",
          "quantity": 1
        },
        {
          "code": "51403",
          "quantity": 1
        },
        {
          "code": "51457",
          "quantity": 1
        },
        {
          "code": "51450",
          "quantity": 1
        },
        {
          "code": "51449",
          "quantity": 1
        }
      ],
      "server_id": 1,
      "min_lvl": 15,
      "max_lvl": 79,
      "type": "ITEM",
      "amount": 0
    },
    {
      "id": 10,
      "img": "https://es.gizmodo.com/app/uploads/2019/05/kgc6dnrc1tuz5xdlxjaq.jpg",
      "name": "Leveling Reward - Axes/Two-Handed Swords",
      "description": "By leveling up and enjoying the content, if you're in the level range 70 to 79, you can claim this reward.",
      "btn_txt": "Claim Reward!",
      "send_item": true,
      "items": [
        {
          "code": "51389",
          "quantity": 1
        },
        {
          "code": "51388",
          "quantity": 1
        },
        {
          "code": "51439",
          "quantity": 1
        },
        {
          "code": "51526",
          "quantity": 1
        },
        {
          "code": "51440",
          "quantity": 1
        },
        {
          "code": "51515",
          "quantity": 1
        },
        {
          "code": "51392",
          "quantity": 1
        },
        {
          "code": "51393",
          "quantity": 1
        },
        {
          "code": "51516",
          "quantity": 1
        },
        {
          "code": "51448",
          "quantity": 1
        },
        {
          "code": "51522",
          "quantity": 1
        }
      ],
      "server_id": 1,
      "min_lvl": 15,
      "max_lvl": 79,
      "type": "ITEM",
      "amount": 0
    },
    {
      "id": 11,
      "img": "https://encrypted-tbn0.gstatic.com/images?q=tbn:ANd9GcRy5rp2ozxs5YbQmibKBN4YiVpZLzi_fRKOgZWyTXKApwUwHpojioaX7w8gWSW_S8MKnik&usqp=CAU",
      "name": "Leveling Reward - Daggers/Maces",
      "description": "By leveling up and enjoying the content, if you're in the level range 70 to 79, you can claim this reward.",
      "btn_txt": "Claim Reward!",
      "send_item": true,
      "items": [
        {
          "code": "51518",
          "quantity": 1
        },
        {
          "code": "51528",
          "quantity": 1
        },
        {
          "code": "51398",
          "quantity": 1
        },
        {
          "code": "51442",
          "quantity": 1
        },
        {
          "code": "51399",
          "quantity": 1
        },
        {
          "code": "51529",
          "quantity": 1
        },
        {
          "code": "51524",
          "quantity": 1
        },
        {
          "code": "51444",
          "quantity": 1
        },
        {
          "code": "51390",
          "quantity": 1
        },
        {
          "code": "51520",
          "quantity": 1
        },
        {
          "code": "51446",
          "quantity": 1
        },
        {
          "code": "51454",
          "quantity": 1
        }
      ],
      "server_id": 1,
      "min_lvl": 15,
      "max_lvl": 79,
      "type": "ITEM",
      "amount": 0
    },
    {
      "id": 12,
      "img": "https://encrypted-tbn0.gstatic.com/images?q=tbn:ANd9GcSyUYhMzg5L5b-YvW47jWahUTyGHRGqhUbXt_Qo6LwpeAqr2UcS_tgx4iPUqRHDS9gob9Y&usqp=CAU",
      "name": "Leveling Reward - Wands",
      "description": "By leveling up and enjoying the content, if you're in the level range 70 to 79, you can claim this reward.",
      "btn_txt": "Claim Reward!",
      "send_item": true,
      "items": [
        {
          "code": "51454",
          "quantity": 1
        },
        {
          "code": "51451",
          "quantity": 1
        },
        {
          "code": "51531",
          "quantity": 1
        },
        {
          "code": "51410",
          "quantity": 1
        }
      ],
      "server_id": 1,
      "min_lvl": 15,
      "max_lvl": 79,
      "type": "ITEM",
      "amount": 0
    },
    {
      "id": 1,
      "img": "https://encrypted-tbn0.gstatic.com/images?q=tbn:ANd9GcTbw94DnB4ZP0L2Q-Is5D0zhT-iMikJ1y5V-g&s",
      "name": "Leveling Promotion - Weapons",
      "description": "Make your progress easier with this amazing promotion! Get relic weapons and level up more effortlessly.",
      "btn_txt": "Get",
      "send_item": true,
      "items": [
        {
          "code": "42944",
          "quantity": 1
        },
        {
          "code": "42946",
          "quantity": 1
        },
        {
          "code": "42948",
          "quantity": 1
        },
        {
          "code": "42943",
          "quantity": 1
        },
        {
          "code": "42945",
          "quantity": 1
        },
        {
          "code": "48716",
          "quantity": 1
        },
        {
          "code": "48718",
          "quantity": 1
        }
      ],
      "server_id": 1,
      "min_lvl": 1,
      "max_lvl": 80,
      "type": "ITEM",
      "amount": 0
    },
    {
      "id": 2,
      "img": "https://chaosboost.com/wp-content/uploads/2024/05/wowclassic-power-leveling.jpg",
      "name": "Claim 800 Frost Emblems Now!",
      "description": "Don’t miss out on this limited-time offer! Get 800 Frost Emblems to enhance your PvE set.",
      "btn_txt": "Get",
      "send_item": true,
      "items": [
        {
          "code": "49426",
          "quantity": 800
        },
        {
          "code": "47241",
          "quantity": 300
        }
      ],
      "server_id": 1,
      "min_lvl": 1,
      "max_lvl": 80,
      "type": "ITEM",
      "amount": 0
    },
    {
      "id": 3,
      "img": "https://wow.zamimg.com/uploads/screenshots/normal/102318-gran-oso-de-blizzard.jpg",
      "name": "Exclusive Mount for Your Account!",
      "description": "Don’t miss out on this chance! Claim a free mount as part of this special promotion. Limited to one account.",
      "btn_txt": "Get",
      "send_item": true,
      "items": [
        {
          "code": "43599",
          "quantity": 1
        },
        {
          "code": "44168",
          "quantity": 1
        }
      ],
      "server_id": 1,
      "min_lvl": 1,
      "max_lvl": 80,
      "type": "ITEM",
      "amount": 0
    },
    {
      "id": 4,
      "img": "https://www.wowchakra.com/wp-content/uploads/2020/04/WowChakraNovelaIlustrada.jpg",
      "name": "Leveling Promotion - Equipment",
      "description": "Discover the Leveo experience! Our promotion is designed to provide you with the ideal gear and help you achieve your goals efficiently and professionally.",
      "btn_txt": "Get",
      "send_item": true,
      "items": [
        {
          "code": "42949",
          "quantity": 1
        },
        {
          "code": "42951",
          "quantity": 1
        },
        {
          "code": "42952",
          "quantity": 1
        },
        {
          "code": "42984",
          "quantity": 1
        },
        {
          "code": "42985",
          "quantity": 1
        },
        {
          "code": "48677",
          "quantity": 1
        },
        {
          "code": "48683",
          "quantity": 1
        },
        {
          "code": "48685",
          "quantity": 1
        },
        {
          "code": "48687",
          "quantity": 1
        },
        {
          "code": "48689",
          "quantity": 1
        },
        {
          "code": "48691",
          "quantity": 1
        },
        {
          "code": "50255",
          "quantity": 1
        }
      ],
      "server_id": 1,
      "min_lvl": 1,
      "max_lvl": 80,
      "type": "ITEM",
      "amount": 0
    },
    {
      "id": 5,
      "img": "https://blz-contentstack-images.akamaized.net/v3/assets/bltf408a0557f4e4998/blt44b9b4635a152dfc/63c71f0ca1a308140627270d/world-of-warcraft-service-character-transfer-section1-feature3.jpg?imwidth=1920&imdensity=2.625",
      "name": "Leveling Promotion - Trinkets and More",
      "description": "Explore our special offer! Find the best trinkets and accessories to enhance your experience and make a difference in every detail.\n",
      "btn_txt": "Get",
      "send_item": true,
      "items": [
        {
          "code": "42985",
          "quantity": 1
        },
        {
          "code": "50255",
          "quantity": 1
        },
        {
          "code": "42991",
          "quantity": 1
        },
        {
          "code": "42992",
          "quantity": 1
        },
        {
          "code": "42947",
          "quantity": 1
        }
      ],
      "server_id": 1,
      "min_lvl": 1,
      "max_lvl": 80,
      "type": "ITEM",
      "amount": 0
    },
    {
      "id": 6,
      "img": "https://cdn.altertime.es/e4f080d2-94e8-4fd0-aa16-a489d183d4bf.png",
      "name": "Exclusive Bag Promotion",
      "description": "Don't miss the chance to grab these exclusive bags and upgrade your inventory!",
      "btn_txt": "Get Now",
      "send_item": true,
      "items": [
        {
          "code": "41600",
          "quantity": 4
        }
      ],
      "server_id": 1,
      "min_lvl": 1,
      "max_lvl": 80,
      "type": "ITEM",
      "amount": 0
    }
  ],
  "pt": [
    {
      "id": 7,
      "img": "https://static.wixstatic.com/media/5dd8a0_67020ed5ab7c46e4be8085fb20563eb7~mv2.webp",
      "name": "Pulo para o Nível 80",
      "description": "Vá direto para o nível 80 e entre na ação! Esqueça o grind e prepare-se para conteúdos épicos agora mesmo.",
      "btn_txt": "Pular Agora!",
      "send_item": false,
      "items": [],
      "server_id": 1,
      "min_lvl": 1,
      "max_lvl": 10,
      "type": "LEVEL",
      "amount": 0
    },
    {
      "id": 8,
      "img": "https://encrypted-tbn0.gstatic.com/images?q=tbn:ANd9GcSvKlw1918kd4HhWR7PtOA5ffUPeFNB8kVVLw&s",
      "name": "Recompensa de Nivelamento - Arcos/Bestas/Armas Arremessáveis/Lanças",
      "description": "Ao subir de nível e aproveitar o conteúdo, se você estiver no intervalo de níveis 70 a 79, poderá reivindicar esta recompensa.",
      "btn_txt": "Reivindicar Recompensa!",
      "send_item": true,
      "items": [
        {
          "code": "51395",
          "quantity": 1
        },
        {
          "code": "51395",
          "quantity": 1
        },
        {
          "code": "51535",
          "quantity": 1
        },
        {
          "code": "51411",
          "quantity": 1
        },
        {
          "code": "51412",
          "quantity": 1
        },
        {
          "code": "51481",
          "quantity": 1
        },
        {
          "code": "51480",
          "quantity": 1
        }
      ],
      "server_id": 1,
      "min_lvl": 15,
      "max_lvl": 79,
      "type": "ITEM",
      "amount": 0
    },
    {
      "id": 9,
      "img": "https://encrypted-tbn0.gstatic.com/images?q=tbn:ANd9GcQQGlJVf0YynsG8lBX2sTbNYXhhkLtJq57iVdjUDuERv0XJu0UhP11JLHGUXpaDS_jYet4&usqp=CAU",
      "name": "Recompensa de Nivelamento - Cajados/Armas de Fogo",
      "description": "Ao subir de nível e aproveitar o conteúdo, se você estiver no intervalo de níveis 70 a 79, poderá reivindicar esta recompensa.",
      "btn_txt": "Reivindicar Recompensa!",
      "send_item": true,
      "items": [
        {
          "code": "51432",
          "quantity": 1
        },
        {
          "code": "51404",
          "quantity": 1
        },
        {
          "code": "51402",
          "quantity": 1
        },
        {
          "code": "51431",
          "quantity": 1
        },
        {
          "code": "51456",
          "quantity": 1
        },
        {
          "code": "51400",
          "quantity": 1
        },
        {
          "code": "51401",
          "quantity": 1
        },
        {
          "code": "51405",
          "quantity": 1
        },
        {
          "code": "51403",
          "quantity": 1
        },
        {
          "code": "51457",
          "quantity": 1
        },
        {
          "code": "51450",
          "quantity": 1
        },
        {
          "code": "51449",
          "quantity": 1
        }
      ],
      "server_id": 1,
      "min_lvl": 15,
      "max_lvl": 79,
      "type": "ITEM",
      "amount": 0
    },
    {
      "id": 10,
      "img": "https://es.gizmodo.com/app/uploads/2019/05/kgc6dnrc1tuz5xdlxjaq.jpg",
      "name": "Recompensa de Nivelamento - Machados/Espadas de Duas Mãos",
      "description": "Ao subir de nível e aproveitar o conteúdo, se você estiver no intervalo de níveis 70 a 79, poderá reivindicar esta recompensa.",
      "btn_txt": "Reivindicar Recompensa!",
      "send_item": true,
      "items": [
        {
          "code": "51389",
          "quantity": 1
        },
        {
          "code": "51388",
          "quantity": 1
        },
        {
          "code": "51439",
          "quantity": 1
        },
        {
          "code": "51526",
          "quantity": 1
        },
        {
          "code": "51440",
          "quantity": 1
        },
        {
          "code": "51515",
          "quantity": 1
        },
        {
          "code": "51392",
          "quantity": 1
        },
        {
          "code": "51393",
          "quantity": 1
        },
        {
          "code": "51516",
          "quantity": 1
        },
        {
          "code": "51448",
          "quantity": 1
        },
        {
          "code": "51522",
          "quantity": 1
        }
      ],
      "server_id": 1,
      "min_lvl": 15,
      "max_lvl": 79,
      "type": "ITEM",
      "amount": 0
    },
    {
      "id": 11,
      "img": "https://encrypted-tbn0.gstatic.com/images?q=tbn:ANd9GcRy5rp2ozxs5YbQmibKBN4YiVpZLzi_fRKOgZWyTXKApwUwHpojioaX7w8gWSW_S8MKnik&usqp=CAU",
      "name": "Recompensa de Nivelamento - Adagas/Maças",
      "description": "Ao subir de nível e aproveitar o conteúdo, se você estiver no intervalo de níveis 70 a 79, poderá reivindicar esta recompensa.",
      "btn_txt": "Reivindicar Recompensa!",
      "send_item": true,
      "items": [
        {
          "code": "51518",
          "quantity": 1
        },
        {
          "code": "51528",
          "quantity": 1
        },
        {
          "code": "51398",
          "quantity": 1
        },
        {
          "code": "51442",
          "quantity": 1
        },
        {
          "code": "51399",
          "quantity": 1
        },
        {
          "code": "51529",
          "quantity": 1
        },
        {
          "code": "51524",
          "quantity": 1
        },
        {
          "code": "51444",
          "quantity": 1
        },
        {
          "code": "51390",
          "quantity": 1
        },
        {
          "code": "51520",
          "quantity": 1
        },
        {
          "code": "51446",
          "quantity": 1
        },
        {
          "code": "51454",
          "quantity": 1
        }
      ],
      "server_id": 1,
      "min_lvl": 15,
      "max_lvl": 79,
      "type": "ITEM",
      "amount": 0
    },
    {
      "id": 12,
      "img": "https://encrypted-tbn0.gstatic.com/images?q=tbn:ANd9GcSyUYhMzg5L5b-YvW47jWahUTyGHRGqhUbXt_Qo6LwpeAqr2UcS_tgx4iPUqRHDS9gob9Y&usqp=CAU",
      "name": "Recompensa de Nivelamento - Varinhas",
      "description": "Ao subir de nível e aproveitar o conteúdo, se você estiver no intervalo de níveis 70 a 79, poderá reivindicar esta recompensa.",
      "btn_txt": "Reivindicar Recompensa!",
      "send_item": true,
      "items": [
        {
          "code": "51454",
          "quantity": 1
        },
        {
          "code": "51451",
          "quantity": 1
        },
        {
          "code": "51531",
          "quantity": 1
        },
        {
          "code": "51410",
          "quantity": 1
        }
      ],
      "server_id": 1,
      "min_lvl": 15,
      "max_lvl": 79,
      "type": "ITEM",
      "amount": 0
    },
    {
      "id": 1,
      "img": "https://encrypted-tbn0.gstatic.com/images?q=tbn:ANd9GcTbw94DnB4ZP0L2Q-Is5D0zhT-iMikJ1y5V-g&s",
      "name": "Promoção de Nivelamento - Armas",
      "description": "Facilite seu progresso com esta promoção incrível! Obtenha armas relíquia e suba de nível com mais facilidade.",
      "btn_txt": "Obter",
      "send_item": true,
      "items": [
        {
          "code": "42944",
          "quantity": 1
        },
        {
          "code": "42946",
          "quantity": 1
        },
        {
          "code": "42948",
          "quantity": 1
        },
        {
          "code": "42943",
          "quantity": 1
        },
        {
          "code": "42945",
          "quantity": 1
        },
        {
          "code": "48716",
          "quantity": 1
        },
        {
          "code": "48718",
          "quantity": 1
        }
      ],
      "server_id": 1,
      "min_lvl": 1,
      "max_lvl": 80,
      "type": "ITEM",
      "amount": 0
    },
    {
      "id": 2,
      "img": "https://chaosboost.com/wp-content/uploads/2024/05/wowclassic-power-leveling.jpg",
      "name": "Resgate 800 Emblemas de Gelo Agora!",
      "description": "Não perca esta oferta limitada! Obtenha 800 emblemas de gelo para fortalecer seu set PvE. Promoção exclusiva para uma conta—aproveite antes que termine!",
      "btn_txt": "Obtener",
      "send_item": true,
      "items": [
        {
          "code": "49426",
          "quantity": 800
        },
        {
          "code": "47241",
          "quantity": 300
        }
      ],
      "server_id": 1,
      "min_lvl": 1,
      "max_lvl": 80,
      "type": "ITEM",
      "amount": 0
    },
    {
      "id": 3,
      "img": "https://wow.zamimg.com/uploads/screenshots/normal/102318-gran-oso-de-blizzard.jpg",
      "name": "Montaria Exclusiva por Conta!",
      "description": "Não perca esta chance! Resgate uma montaria grátis como parte desta promoção especial.",
      "btn_txt": "Obtener",
      "send_item": true,
      "items": [
        {
          "code": "43599",
          "quantity": 1
        },
        {
          "code": "44168",
          "quantity": 1
        }
      ],
      "server_id": 1,
      "min_lvl": 1,
      "max_lvl": 80,
      "type": "ITEM",
      "amount": 0
    },
    {
      "id": 4,
      "img": "https://www.wowchakra.com/wp-content/uploads/2020/04/WowChakraNovelaIlustrada.jpg",
      "name": "Promoção de Leveling - Equipamentos",
      "description": "Descubra a experiência Leveo! Nossa promoção foi projetada para fornecer o equipamento ideal e ajudá-lo a alcançar seus objetivos de forma eficiente e profissional.",
      "btn_txt": "Obter",
      "send_item": true,
      "items": [
        {
          "code": "42949",
          "quantity": 1
        },
        {
          "code": "42951",
          "quantity": 1
        },
        {
          "code": "42952",
          "quantity": 1
        },
        {
          "code": "42984",
          "quantity": 1
        },
        {
          "code": "42985",
          "quantity": 1
        },
        {
          "code": "48677",
          "quantity": 1
        },
        {
          "code": "48683",
          "quantity": 1
        },
        {
          "code": "48685",
          "quantity": 1
        },
        {
          "code": "48687",
          "quantity": 1
        },
        {
          "code": "48689",
          "quantity": 1
        },
        {
          "code": "48691",
          "quantity": 1
        },
        {
          "code": "50255",
          "quantity": 1
        }
      ],
      "server_id": 1,
      "min_lvl": 1,
      "max_lvl": 80,
      "type": "ITEM",
      "amount": 0
    },
    {
      "id": 5,
      "img": "https://blz-contentstack-images.akamaized.net/v3/assets/bltf408a0557f4e4998/blt44b9b4635a152dfc/63c71f0ca1a308140627270d/world-of-warcraft-service-character-transfer-section1-feature3.jpg?imwidth=1920&imdensity=2.625",
      "name": "Promoção de Leveling - Acessórios e Mais",
      "description": "Explore nossa oferta especial! Encontre os melhores acessórios e itens para aprimorar sua experiência e fazer a diferença em cada detalhe.",
      "btn_txt": "Obter",
      "send_item": true,
      "items": [
        {
          "code": "42985",
          "quantity": 1
        },
        {
          "code": "50255",
          "quantity": 1
        },
        {
          "code": "42991",
          "quantity": 1
        },
        {
          "code": "42992",
          "quantity": 1
        },
        {
          "code": "42947",
          "quantity": 1
        }
      ],
      "server_id": 1,
      "min_lvl": 1,
      "max_lvl": 80,
      "type": "ITEM",
      "amount": 0
    },
    {
      "id": 6,
      "img": "https://cdn.altertime.es/e4f080d2-94e8-4fd0-aa16-a489d183d4bf.png",
      "name": "Promoção Exclusiva de Bolsas",
      "description": "Não perca a chance de conseguir essas bolsas exclusivas e melhore seu inventário!",
      "btn_txt": "Obter Agora",
      "send_item": true,
      "items": [
        {
          "code": "41600",
          "quantity": 4
        }
      ],
      "server_id": 1,
      "min_lvl": 1,
      "max_lvl": 80,
      "type": "ITEM",
      "amount": 0
    }
  ]
}